simple_functions/__init__.py
simple_functions/simple_functions.py
simple_functions-0.0.3.dist-info/DESCRIPTION.rst
simple_functions-0.0.3.dist-info/METADATA
simple_functions-0.0.3.dist-info/RECORD
simple_functions-0.0.3.dist-info/WHEEL
simple_functions-0.0.3.dist-info/metadata.json
simple_functions-0.0.3.dist-info/top_level.txt
