Metadata-Version: 2.0
Name: simple-functions
Version: 0.0.3
Summary: Simple Functions to create IDs for objects
Home-page: UNKNOWN
Author: Ishu Kumar
Author-email: ishu.kumars@gmail.com
License: UNKNOWN
Keywords: python,first package,ids
Platform: UNKNOWN
Classifier: Development Status :: 2 - Pre-Alpha
Classifier: Intended Audience :: Education
Classifier: Programming Language :: Python :: 2
Classifier: Programming Language :: Python :: 3
Classifier: Operating System :: MacOS :: MacOS X
Classifier: Operating System :: Microsoft :: Windows
